Metadata-Version: 2.1
Name: upstride-argparse
Version: 1.0.0
Summary: Simple and efficient argument parser for every python projects
Home-page: https://github.com/UpStride/betterargparse
Author: Upstride
Author-email: pypi@upstride.io
License: UNKNOWN
Platform: UNKNOWN
Classifier: Programming Language :: Python :: 3
Classifier: License :: OSI Approved :: MIT License
Classifier: Operating System :: OS Independent
